alira/__init__.py
alira/instance.py
alira/pipeline.py
alira/common/__init__.py
alira/common/database.py
alira/common/marked_attributes.py
alira/common/smtp.py
alira/common/utils.py
alira/modules/__init__.py
alira/modules/email.py
alira/modules/flagging.py
alira/modules/map.py
alira/modules/module.py
alira/modules/notification.py
alira/modules/rest.py
alira/modules/s3.py
alira/modules/selection.py
alira/modules/twilio.py
levatas_alira-5.0.2.dist-info/METADATA
levatas_alira-5.0.2.dist-info/WHEEL
levatas_alira-5.0.2.dist-info/top_level.txt
levatas_alira-5.0.2.dist-info/RECORD
