Metadata-Version: 2.1
Name: levatas-alira
Version: 5.0.2
Summary: Alira
Home-page: https://github.com/vinsa-ai/alira
Author: Levatas
Author-email: svpino@gmail.com
License: UNKNOWN
Platform: UNKNOWN
Requires-Dist: PyYAML (<6.1,>=6.0)
Requires-Dist: redis (<4.5,>=4.4)
Requires-Dist: rq (<1.13,>=1.12)
Requires-Dist: rq-scheduler (<0.12,>=0.11)
Requires-Dist: requests (<2.29,>=2.28)
Requires-Dist: boto3
Requires-Dist: twilio
Requires-Dist: jmespath (<1.1,>=1.0)
Requires-Dist: sqlalchemy (<1.5,>=1.4)
Requires-Dist: pymysql (<1.1,>=1.0)
